dircolors/__init__.py
dircolors/_defaults.py
dircolors/_util.py
dircolors/dircolors.py
dircolors/pyls/__init__.py
dircolors/pyls/__main__.py
dircolors/pyls/pyls.py
dircolors-0.0.4.dist-info/entry_points.txt
dircolors-0.0.4.dist-info/LICENSE.txt
dircolors-0.0.4.dist-info/WHEEL
dircolors-0.0.4.dist-info/METADATA
dircolors-0.0.4.dist-info/RECORD
