Metadata-Version: 2.1
Name: dircolors
Version: 0.0.4
Summary: Python library to colorize filenames in a terminal based on their type 
Home-page: https://github.com/aswild/pydircolors
License: UNKNOWN
Author: Allen Wild
Author-email: allenwild93@gmail.com
Requires-Python: >=3.3
Classifier: Development Status :: 3 - Alpha
Classifier: License :: OSI Approved :: Apache Software License
Classifier: Programming Language :: Python :: 3 :: Only
Classifier: Programming Language :: Python :: 3.3
Classifier: Programming Language :: Python :: 3.4
Classifier: Programming Language :: Python :: 3.5
Classifier: Programming Language :: Python :: 3.6
Classifier: Programming Language :: Python :: 3.7
Classifier: Operating System :: POSIX
Classifier: Operating System :: POSIX :: Linux
